Metadata-Version: 2.1
Name: zhouyuqin-python-sdk-core
Version: 0.1.0
Summary: The core module of zhouyuqin Python SDK.
Home-page: 
Author: zhouyuqin
Author-email: 
License: Apache License 2.0
Platform: any
Requires-Dist: jmespath (<1.0.0,>=0.9.3)
Requires-Dist: cryptography (>=2.6.0)
